blescope/__init__.py
blescope/__version__.py
blescope/api/__init__.py
blescope/api/app.py
blescope/api/dependencies.py
blescope/api/log_router.py
blescope/api/static_files.py
blescope/api/websocket_manager.py
blescope/scanning/application/commands/__init__.py
blescope/scanning/application/ports/__init__.py
blescope/scanning/application/ports/bluetooth_scanner.py
blescope/scanning/application/ports/device_repository.py
blescope/scanning/application/ports/scan_repository.py
blescope/scanning/application/queries/__init__.py
blescope/scanning/application/queries/get_discovered_devices.py
blescope/scanning/application/queries/get_scan_status.py
blescope/scanning/application/services/__init__.py
blescope/scanning/application/services/scan_manager.py
blescope/scanning/domain/__init__.py
blescope/scanning/domain/discovered_device.py
blescope/scanning/domain/events.py
blescope/scanning/domain/exceptions.py
blescope/scanning/domain/scan.py
blescope/scanning/infrastructure/adapters/__init__.py
blescope/scanning/infrastructure/adapters/bleak_scanner_adapter.py
blescope/scanning/infrastructure/adapters/in_memory_discovered_device_repository.py
blescope/scanning/infrastructure/adapters/in_memory_scan_repository.py
blescope/scanning/infrastructure/web/__init__.py
blescope/scanning/infrastructure/web/scan_router.py
blescope/shared/__init__.py
blescope/shared/domain/__init__.py
blescope/shared/domain/base_types.py
blescope/shared/events/__init__.py
blescope/shared/events/event_bus.py
blescope/shared/infrastructure/__init__.py
blescope/shared/infrastructure/config.py
blescope/shared/infrastructure/logging_config.py
blescope/utils/__init__.py
blescope/utils/_compat.py
blescope-0.0.0.dist-info/METADATA
blescope-0.0.0.dist-info/WHEEL
blescope-0.0.0.dist-info/RECORD
