Metadata-Version: 2.3
Name: blescope
Version: 0.0.0
Summary: Like a telescope for Bluetooth Low Energy devices
License: MIT
Author: Lionel H
Author-email: me@nullbyte.be
Requires-Python: >=3.13,<4.0.0
Classifier: License :: OSI Approved :: MIT License
Classifier: Programming Language :: Python :: 3
Classifier: Programming Language :: Python :: 3.13
Requires-Dist: bleak (>=1.1.1,<2.0.0)
Requires-Dist: fastapi[standard] (>=0.116.1,<0.117.0)
Requires-Dist: orjson (>=3.11.3,<4.0.0)
Requires-Dist: pydantic (>=2.11.9,<3.0.0)
Requires-Dist: pydantic-settings (>=2.10.1,<3.0.0)
Requires-Dist: pyserde (>=0.25.1,<0.26.0)
Requires-Dist: uvicorn[standard] (>=0.35.0,<0.36.0)
